hmm_cli.py
hmm_git_safety-1.0.0.dist-info/licenses/LICENSE
hmm_git_safety-1.0.0.dist-info/METADATA
hmm_git_safety-1.0.0.dist-info/WHEEL
hmm_git_safety-1.0.0.dist-info/entry_points.txt
hmm_git_safety-1.0.0.dist-info/top_level.txt
hmm_git_safety-1.0.0.dist-info/RECORD
