Metadata-Version: 2.4
Name: hmm-git-safety
Version: 1.0.0
Summary: A safety wrapper for git push that prevents accidental pushes to origin without branch name
Author: hmm contributors
Project-URL: Homepage, https://github.com/vishesh9131/hmm
Project-URL: Repository, https://github.com/vishesh9131/hmm
Keywords: git,safety,git-push,git-wrapper,developer-tools,cli
Classifier: Development Status :: 4 - Beta
Classifier: Intended Audience :: Developers
Classifier: Topic :: Software Development :: Version Control :: Git
Classifier: Programming Language :: Python :: 3
Classifier: Programming Language :: Python :: 3.6
Classifier: Programming Language :: Python :: 3.7
Classifier: Programming Language :: Python :: 3.8
Classifier: Programming Language :: Python :: 3.9
Classifier: Programming Language :: Python :: 3.10
Classifier: Operating System :: MacOS
Classifier: Operating System :: POSIX :: Linux
Classifier: Operating System :: Microsoft :: Windows
Requires-Python: >=3.6
License-File: LICENSE
Dynamic: license-file
